txmd/__init__.py
txmd/cli.py
txmd/toc.py
txmd-0.4.0.dist-info/LICENSE
txmd-0.4.0.dist-info/METADATA
txmd-0.4.0.dist-info/WHEEL
txmd-0.4.0.dist-info/entry_points.txt
txmd-0.4.0.dist-info/RECORD
