Metadata-Version: 2.1
Name: txmd
Version: 0.4.0
Summary: A textual markdown viewer CLI
Home-page: https://github.com/guglielmo/txmd
License: MIT
Keywords: markdown,terminal,cli,viewer,textual
Author: Guglielmo Celata
Author-email: guglielmo.celata@gmail.com
Requires-Python: >=3.9,<4.0
Classifier: Development Status :: 3 - Alpha
Classifier: Environment :: Console
Classifier: Intended Audience :: Developers
Classifier: Intended Audience :: End Users/Desktop
Classifier: License :: OSI Approved :: MIT License
Classifier: Programming Language :: Python :: 3
Classifier: Programming Language :: Python :: 3.9
Classifier: Programming Language :: Python :: 3.10
Classifier: Programming Language :: Python :: 3.11
Classifier: Programming Language :: Python :: 3.12
Classifier: Topic :: Terminals
Classifier: Topic :: Text Processing :: Markup
Classifier: Topic :: Utilities
Requires-Dist: Markdown (>=3.7,<4.0)
Requires-Dist: rich (>=13.9.4,<14.0.0)
Requires-Dist: textual (>=0.86.3,<0.87.0)
Requires-Dist: typer (>=0.13.1,<0.14.0)
Project-URL: Documentation, https://github.com/guglielmo/txmd#readme
Project-URL: Repository, https://github.com/guglielmo/txmd
